xschem/dsm/src/DFF.v
// ========================================================
// Basic Building Block: D Flip-Flop with Active High Reset
// ========================================================

module DFF (
    input wire clk,
    input wire rst,
    input wire d,
    output reg q,
    output wire q_bar
);
    assign q_bar = ~q;

    always @(posedge clk or posedge rst) begin
        if (rst)
            q <= 1'b0;
        else
            q <= d;
    end
endmodule

schematic/freq_divider/src/Output_Div2.v
// ====================================================
// Module 5: Output Divide-by-2 & Duty Cycle Correction
// ====================================================
//`include "DFF.v"

module Output_Div2 (
    input wire clk,
    input wire rst,
    output wire out
);
    wire q_out, q_bar_out;

    DFF dff_out (
        .clk(clk),
        .rst(rst),
        .d(q_bar_out), // Toggles every rising edge
        .q(q_out),
        .q_bar(q_bar_out)
    );

    assign out = q_out;
endmodule

schematic/dsm/src/Modulus_Controller.v
// ===============================================
// Module 4: Modulus Controller
// Decodes counter state to control Prescaler (MC)
// ===============================================

module Modulus_Controller (
    input wire b, // LSB
    input wire c,
    input wire d, // MSB
    input wire c_bar,
    input wire d_bar,
    input wire select_in,  // 1->240, 0->248
    output wire mc
);
    wire logic_0, logic_1, logic_2;

    assign logic_0 = b;
    assign logic_1 = c_bar & d_bar;
    assign logic_2 = c & d & select_in;
    
    assign mc = logic_0 | logic_1 | logic_2;
endmodule

xschem/dsm/src/JK_FF.v
// =========================================================
// Basic Building Block: JK Flip-Flop (Constructed from DFF)
// =========================================================
//`include "DFF.v"

module JK_FF (
    input wire clk,
    input wire rst,
    input wire j,
    input wire k,
    output wire q,
    output wire q_bar
);
    wire d_in;
    wire q_curr, q_bar_curr;
    
    // Logic: D = J & ~Q | ~K & Q
    assign d_in = (j & q_bar_curr) | (~k & q_curr);
    
    DFF dff_inst (
        .clk(clk),
        .rst(rst),
        .d(d_in),
        .q(q),
        .q_bar(q_bar)
    );
    
    // Internal wiring to allow feedback
    assign q_curr = q;
    assign q_bar_curr = q_bar;
endmodule

xschem/dsm/src/Mod7_Counter.v
// =================================================
// Module 3: Mod-7 Synchronous Counter (Using JK-FF)
// Sequence: 000 -> 001 -> ... -> 110 -> 000
// =================================================
//`include "JK_FF.v"

module Mod7_Counter (
    input wire clk,
    input wire rst,
    output wire bit1, bit2,
    output wire bit3, bit4,
    output wire out
);
    // Wires for feedback logic

    wire gate1_out, gate2_out, gate3_out;
    
    // Gate connections derived for structural implementation:
    assign gate1_out = bit4 | bit3;
    assign gate2_out = bit1 | out;
    assign gate3_out = bit1 & bit2;
    
    /* verilator lint_off PINCONNECTEMPTY */
    JK_FF jk1 (.clk(clk), .rst(rst), .j(gate1_out), .k(1'b1), .q(bit1), .q_bar());
    /* verilator lint_on PINCONNECTEMPTY */
    JK_FF jk2 (.clk(clk), .rst(rst), .j(bit1), .k(gate2_out), .q(bit2), .q_bar(bit3));
    JK_FF jk3 (.clk(clk), .rst(rst), .j(gate3_out), .k(bit2), .q(out), .q_bar(bit4));
endmodule

xschem/freq_divider/src/Prescaler_4_5.v
// ===============================================================
// Module 2: 4/5 Pre-scaler (Dual Modulus Divider)
// Logic: Divides by 4 normally. If MC=0, swallows a pulse (Div 5).
// ===============================================================
//`include "DFF.v"

module Prescaler_4_5 (
    input wire clk,     // Input from Div-4 block
    input wire rst,
    input wire mc,     // Modulus Control
    output wire out    // Output to Mod-7 Counter
);
    wire q1_n, q2, q3;
    wire d1, d2, d3;
    wire mc_gated;

    // Implementing gate structure:
    assign d2 = q1_n;
    assign d3 = q2;
    
    // Logic to enable division by 5 when MC is low
    assign mc_gated = mc | q3; 
    assign d1 = q2 & mc_gated;

    /* verilator lint_off PINCONNECTEMPTY */
    DFF ff1 (.clk(clk), .rst(rst), .d(d1), .q(), .q_bar(q1_n));
    DFF ff2 (.clk(clk), .rst(rst), .d(d2), .q(q2), .q_bar());
    DFF ff3 (.clk(clk), .rst(rst), .d(d3), .q(q3), .q_bar());
    /* verilator lint_on PINCONNECTEMPTY */

    assign out = q3; // Output taken from last stage
endmodule

xschem/dsm/src/Divide_by_4.v
// =============================================
// Module 1: Divide-by-4 (Using 2 Cascaded DFFs)
// =============================================
//`include "DFF.v"

module Divide_by_4 (
    input wire in,
    input wire rst,
    output wire out
);
    wire q1, q1_bar;
    wire q2, q2_bar;

    // Stage 1: Divide by 2
    DFF dff1 (
        .clk(in),
        .rst(rst),
        .d(q1_bar), // Feedback inverted output
        .q(q1),
        .q_bar(q1_bar)
    );

    // Stage 2: Divide by 2 (Clocked by output of Stage 1)
    DFF dff2 (
        .clk(q1),
        .rst(rst),
        .d(q2_bar), // Feedback inverted output
        .q(q2), // Output is "out"
        .q_bar(q2_bar)
    );

    assign out = q2;
endmodule

schematic/dsm/src/Frequency_Divider_240_248.v
// ============================================================
// TOP MODULE: Connecting all blocks
// ============================================================
//`include "Divide_by_4.v"
//`include "Prescaler_4_5.v"
//`include "Mod7_Counter.v"
//`include "Modulus_Controller.v"
//`include "Output_Div2.v"

module Frequency_Divider_240_248 (
    input wire freq_in,       // Frequency Input from VCO
    input wire reset,         // Global Reset
    input wire select_mode,   // 1 for Div-240, 0 for Div-248
    output wire freq_out      // Frequency Output to PFD
);

    // Interconnect wires
    wire dmd_in;                 // Output of Div-4, Input to Prescaler
    wire clk_jk;                 // Output of Prescaler, Clock for Mod7-Counter
    wire mc_sig;                 // Modulus control signal
    wire b, c, d, c_bar, d_bar;  // Counter bits

    // 1. Divide by 4
    Divide_by_4 div4 (
        .in(freq_in),
        .rst(reset),
        .out(dmd_in)
    );

    // 2. Prescaler 4/5
    Prescaler_4_5 pre45 (
        .clk(dmd_in),
        .rst(reset),
        .mc(mc_sig),
        .out(clk_jk)
    );

    // 3. Mod-7 Counter
    Mod7_Counter mod7 (
        .clk(clk_jk),
        .rst(reset),
        .bit1(b),
        .bit2(c),
        .bit3(c_bar),
        .bit4(d_bar),
        .out(d)
    );

    // 4. Modulus Controller
    Modulus_Controller mod_ctrl (
        .b(b),
        .c(c),
        .d(d),
        .c_bar(c_bar),
        .d_bar(d_bar),
        .select_in(select_mode),
        .mc(mc_sig)
    );

    // 5. Final Divide-by-2 (Duty Cycle Corrector)
    Output_Div2 out_stg (
        .clk(d), 
        .rst(reset),
        .out(freq_out)
    );

endmodule

schematic/freq_divider/testbenches/tb_Frequency_Divider_240_248.v
`timescale 1ns/1ps
`include "Frequency_Divider_240_248.v"

module tb_Frequency_Divider_240_248;
    // Inputs
    reg freq_in;
    reg reset;
    reg select_mode;
    // Outputs
    wire freq_out;

    // Instantiate Top Level
    Frequency_Divider_240_248 uut (
        .freq_in(freq_in), 
        .reset(reset), 
        .select_mode(select_mode), 
        .freq_out(freq_out)
    );

    // Generate Clock: 100MHz (10ns period)
    always #5 freq_in = ~freq_in; 

    // Variables to store time stamps
    real t1, t2;
    real period, frequency_mhz;

    initial begin
        $dumpfile("tb_Frequency_Divider_240_248.vcd");
        $dumpvars;

        // TEST CASE 1: Divide by 248 (Select = 0)
        freq_in = 0;
        reset = 1;
        select_mode = 0; 
        // Wait 20ns for global reset to finish
        #20;
        reset = 0;

        // Wait for the output to stabilize or toggle at least once
        @(posedge freq_out);
        // Capture time of first rising edge
        @(posedge freq_out); 
        t1 = $realtime;
        // Capture time of second rising edge
        @(posedge freq_out); 
        t2 = $realtime;

        // Calculate
        period = t2 - t1;
        
        $display("--------------------------------");
        $display("Mode: Divide-by-248 (Select=0)");
        $display("Time between edges: %0.2f ns", period);
        $display("Expected Period:    2480.00 ns");
        $display("--------------------------------"); 
        
        // TEST CASE 2: Divide by 240 (Select = 1)
        select_mode = 1;
        reset = 1; // Pulse reset when switching modes
        // Wait 20ns for global reset to finish
        #20;
        reset = 0;
        
        // Wait for the output to stabilize or toggle at least once
        @(posedge freq_out);
        // Capture time of first rising edge
        @(posedge freq_out); 
        t1 = $realtime;
        // Capture time of second rising edge
        @(posedge freq_out); 
        t2 = $realtime;

        // Calculate
        period = t2 - t1;
        
        $display("--------------------------------");
        $display("Mode: Divide-by-240 (Select=1)");
        $display("Time between edges: %0.2f ns", period);
        $display("Expected Period:    2400.00 ns");
        $display("--------------------------------"); 

        $finish;
    end
endmodule

schematic/freq_divider/src/tb_Frequency_Divider_240_248.vcd
$date
	Sat Feb 21 19:48:40 2026
$end
$version
	Icarus Verilog
$end
$timescale
	1ps
$end
$scope module tb_Frequency_Divider_240_248 $end
$var wire 1 ! freq_out $end
$var reg 1 " freq_in $end
$var reg 1 # reset $end
$var reg 1 $ select_mode $end
$var real 1 % period $end
$var real 1 & t1 $end
$var real 1 ' t2 $end
$scope module uut $end
$var wire 1 " freq_in $end
$var wire 1 # reset $end
$var wire 1 $ select_mode $end
$var wire 1 ( mc_sig $end
$var wire 1 ! freq_out $end
$var wire 1 ) dmd_in $end
$var wire 1 * d_bar $end
$var wire 1 + d $end
$var wire 1 , clk_jk $end
$var wire 1 - c_bar $end
$var wire 1 . c $end
$var wire 1 / b $end
$scope module div4 $end
$var wire 1 " in $end
$var wire 1 ) out $end
$var wire 1 # rst $end
$var wire 1 0 q2_bar $end
$var wire 1 1 q2 $end
$var wire 1 2 q1_bar $end
$var wire 1 3 q1 $end
$scope module dff1 $end
$var wire 1 " clk $end
$var wire 1 2 d $end
$var wire 1 2 q_bar $end
$var wire 1 # rst $end
$var reg 1 3 q $end
$upscope $end
$scope module dff2 $end
$var wire 1 3 clk $end
$var wire 1 0 d $end
$var wire 1 0 q_bar $end
$var wire 1 # rst $end
$var reg 1 1 q $end
$upscope $end
$upscope $end
$scope module mod7 $end
$var wire 1 4 gate1_out $end
$var wire 1 5 gate2_out $end
$var wire 1 6 gate3_out $end
$var wire 1 # rst $end
$var wire 1 + out $end
$var wire 1 , clk $end
$var wire 1 * bit4 $end
$var wire 1 - bit3 $end
$var wire 1 . bit2 $end
$var wire 1 / bit1 $end
$scope module jk1 $end
$var wire 1 7 d_in $end
$var wire 1 4 j $end
$var wire 1 8 k $end
$var wire 1 9 q_bar_curr $end
$var wire 1 : q_curr $end
$var wire 1 # rst $end
$var wire 1 ; q_bar $end
$var wire 1 / q $end
$var wire 1 , clk $end
$scope module dff_inst $end
$var wire 1 7 d $end
$var wire 1 ; q_bar $end
$var wire 1 # rst $end
$var wire 1 , clk $end
$var reg 1 / q $end
$upscope $end
$upscope $end
$scope module jk2 $end
$var wire 1 < d_in $end
$var wire 1 / j $end
$var wire 1 5 k $end
$var wire 1 = q_bar_curr $end
$var wire 1 > q_curr $end
$var wire 1 # rst $end
$var wire 1 - q_bar $end
$var wire 1 . q $end
$var wire 1 , clk $end
$scope module dff_inst $end
$var wire 1 < d $end
$var wire 1 - q_bar $end
$var wire 1 # rst $end
$var wire 1 , clk $end
$var reg 1 . q $end
$upscope $end
$upscope $end
$scope module jk3 $end
$var wire 1 ? d_in $end
$var wire 1 6 j $end
$var wire 1 . k $end
$var wire 1 @ q_bar_curr $end
$var wire 1 A q_curr $end
$var wire 1 # rst $end
$var wire 1 * q_bar $end
$var wire 1 + q $end
$var wire 1 , clk $end
$scope module dff_inst $end
$var wire 1 ? d $end
$var wire 1 * q_bar $end
$var wire 1 # rst $end
$var wire 1 , clk $end
$var reg 1 + q $end
$upscope $end
$upscope $end
$upscope $end
$scope module mod_ctrl $end
$var wire 1 / b $end
$var wire 1 . c $end
$var wire 1 - c_bar $end
$var wire 1 + d $end
$var wire 1 * d_bar $end
$var wire 1 B logic_0 $end
$var wire 1 C logic_1 $end
$var wire 1 D logic_2 $end
$var wire 1 ( mc $end
$var wire 1 $ select_in $end
$upscope $end
$scope module out_stg $end
$var wire 1 + clk $end
$var wire 1 ! out $end
$var wire 1 # rst $end
$var wire 1 E q_out $end
$var wire 1 F q_bar_out $end
$scope module dff_out $end
$var wire 1 + clk $end
$var wire 1 F d $end
$var wire 1 F q_bar $end
$var wire 1 # rst $end
$var reg 1 E q $end
$upscope $end
$upscope $end
$scope module pre45 $end
$var wire 1 ) clk $end
$var wire 1 G d1 $end
$var wire 1 H d2 $end
$var wire 1 I d3 $end
$var wire 1 ( mc $end
$var wire 1 J mc_gated $end
$var wire 1 , out $end
$var wire 1 # rst $end
$var wire 1 K q3 $end
$var wire 1 L q2 $end
$var wire 1 M q1_n $end
$scope module ff1 $end
$var wire 1 ) clk $end
$var wire 1 G d $end
$var wire 1 M q_bar $end
$var wire 1 # rst $end
$var reg 1 N q $end
$upscope $end
$scope module ff2 $end
$var wire 1 ) clk $end
$var wire 1 H d $end
$var wire 1 O q_bar $end
$var wire 1 # rst $end
$var reg 1 L q $end
$upscope $end
$scope module ff3 $end
$var wire 1 ) clk $end
$var wire 1 I d $end
$var wire 1 P q_bar $end
$var wire 1 # rst $end
$var reg 1 K q $end
$upscope $end
$upscope $end
$upscope $end
$upscope $end
$enddefinitions $end
$comment Show the parameter values. $end
$dumpall
$end
#0
$dumpvars
1P
1O
0N
1M
0L
0K
1J
0I
1H
0G
1F
0E
0D
1C
0B
0A
1@
0?
0>
1=
0<
1;
0:
19
18
17
06
05
14
03
12
01
10
0/
0.
1-
0,
0+
1*
0)
1(
r0 '
r0 &
r0 %
0$
1#
0"
0!
$end
#5000
1"
#10000
0"
#15000
1"
#20000
0"
0#
#25000
0O
1G
1I
1L
00
1)
11
02
13
1"
#30000
0"
#35000
12
03
1"
#40000
0"
#45000
10
0)
01
02
13
1"
#50000
0"
#55000
12
03
1"
#60000
0"
#65000
07
1<
09
0;
15
1B
1:
1/
0H
0M
0P
1N
1,
1K
00
1)
11
02
13
1"
#70000
0"
#75000
12
03
1"
#80000
0"
#85000
10
0)
01
02
13
1"
#90000
0"
#95000
12
03
1"
#100000
0"
#105000
1O
0G
0I
0L
00
1)
11
02
13
1"
#110000
0"
#115000
12
03
1"
#120000
0"
#125000
10
0)
01
02
13
1"
#130000
0"
#135000
12
03
1"
#140000
0"
#145000
1H
1M
1P
0N
0,
0K
00
1)
11
02
13
1"
#150000
0"
#155000
12
03
1"
#160000
0"
#165000
10
0)
01
02
13
1"
#170000
0"
#175000
12
03
1"
#180000
0"
#185000
0O
1G
1I
1L
00
1)
11
02
13
1"
#190000
0"
#195000
12
03
1"
#200000
0"
#205000
10
0)
01
02
13
1"
#210000
0"
#215000
12
03
1"
#220000
0"
#225000
0(
17
1<
0C
19
1;
05
0=
0-
0B
0:
0/
1>
1.
0H
0M
0P
1N
1,
1K
00
1)
11
02
13
1"
#230000
0"
#235000
12
03
1"
#240000
0"
#245000
10
0)
01
02
13
1"
#250000
0"
#255000
12
03
1"
#260000
0"
#265000
1O
0G
0I
0L
00
1)
11
02
13
1"
#270000
0"
#275000
12
03
1"
#280000
0"
#285000
10
0)
01
02
13
1"
#290000
0"
#295000
12
03
1"
#300000
0"
#305000
1H
1M
1P
0J
0N
0,
0K
00
1)
11
02
13
1"
#310000
0"
#315000
12
03
1"
#320000
0"
#325000
10
0)
01
02
13
1"
#330000
0"
#335000
12
03
1"
#340000
0"
#345000
0O
1I
1L
00
1)
11
02
13
1"
#350000
0"
#355000
12
03
1"
#360000
0"
#365000
10
0)
01
02
13
1"
#370000
0"
#375000
12
03
1"
#380000
0"
#385000
0<
07
1?
1(
09
0;
16
15
1B
1:
1/
1G
0P
1J
1,
1K
00
1)
11
02
13
1"
#390000
0"
#395000
12
03
1"
#400000
0"
#405000
10
0)
01
02
13
1"
#410000
0"
#415000
12
03
1"
#420000
0"
#425000
0H
0M
1N
00
1)
11
02
13
1"
#430000
0"
#435000
12
03
1"
#440000
0"
#445000
10
0)
01
02
13
1"
#450000
0"
#455000
12
03
1"
#460000
0"
#465000
1O
0G
0I
0L
00
1)
11
02
13
1"
#470000
0"
#475000
12
03
1"
#480000
0"
#485000
10
0)
01
02
13
1"
#490000
0"
#495000
12
03
1"
#500000
0"
#505000
1P
1H
1M
0,
0K
0N
00
1)
11
02
13
1"
#510000
0"
#515000
12
03
1"
#520000
0"
#525000
10
0)
01
02
13
1"
#530000
0"
#535000
12
03
1"
#540000
0"
#545000
0O
1G
1I
1L
00
1)
11
02
13
1"
#550000
0"
#555000
12
03
1"
#560000
0"
#565000
10
0)
01
02
13
1"
#570000
0"
#575000
12
03
1"
#580000
0"
#585000
0F
1!
1E
17
0(
19
1;
1=
1-
06
0@
0*
0B
0:
0/
0>
0.
1A
1+
0P
0H
0M
1,
1K
1N
00
1)
11
02
13
1"
#590000
0"
#595000
12
03
1"
#600000
0"
#605000
10
0)
01
02
13
1"
#610000
0"
#615000
12
03
1"
#620000
0"
#625000
1O
0G
0I
0L
00
1)
11
02
13
1"
#630000
0"
#635000
12
03
1"
#640000
0"
#645000
10
0)
01
02
13
1"
#650000
0"
#655000
12
03
1"
#660000
0"
#665000
1P
0J
1H
1M
0,
0K
0N
00
1)
11
02
13
1"
#670000
0"
#675000
12
03
1"
#680000
0"
#685000
10
0)
01
02
13
1"
#690000
0"
#695000
12
03
1"
#700000
0"
#705000
0O
1I
1L
00
1)
11
02
13
1"
#710000
0"
#715000
12
03
1"
#720000
0"
#725000
10
0)
01
02
13
1"
#730000
0"
#735000
12
03
1"
#740000
0"
#745000
07
1<
1(
09
0;
1B
1:
1/
1G
0P
1J
1,
1K
00
1)
11
02
13
1"
#750000
0"
#755000
12
03
1"
#760000
0"
#765000
10
0)
01
02
13
1"
#770000
0"
#775000
12
03
1"
#780000
0"
#785000
0H
0M
1N
00
1)
11
02
13
1"
#790000
0"
#795000
12
03
1"
#800000
0"
#805000
10
0)
01
02
13
1"
#810000
0"
#815000
12
03
1"
#820000
0"
#825000
1O
0G
0I
0L
00
1)
11
02
13
1"
#830000
0"
#835000
12
03
1"
#840000
0"
#845000
10
0)
01
02
13
1"
#850000
0"
#855000
12
03
1"
#860000
0"
#865000
1H
1M
1P
0N
0,
0K
00
1)
11
02
13
1"
#870000
0"
#875000
12
03
1"
#880000
0"
#885000
10
0)
01
02
13
1"
#890000
0"
#895000
12
03
1"
#900000
0"
#905000
0O
1G
1I
1L
00
1)
11
02
13
1"
#910000
0"
#915000
12
03
1"
#920000
0"
#925000
10
0)
01
02
13
1"
#930000
0"
#935000
12
03
1"
#940000
0"
#945000
0?
0<
0(
04
19
1;
0=
0-
0B
0:
0/
1>
1.
0H
0M
0P
1N
1,
1K
00
1)
11
02
13
1"
#950000
0"
#955000
12
03
1"
#960000
0"
#965000
10
0)
01
02
13
1"
#970000
0"
#975000
12
03
1"
#980000
0"
#985000
1O
0G
0I
0L
00
1)
11
02
13
1"
#990000
0"
#995000
12
03
1"
#1000000
0"
#1005000
10
0)
01
02
13
1"
#1010000
0"
#1015000
12
03
1"
#1020000
0"
#1025000
1H
1M
1P
0J
0N
0,
0K
00
1)
11
02
13
1"
#1030000
0"
#1035000
12
03
1"
#1040000
0"
#1045000
10
0)
01
02
13
1"
#1050000
0"
#1055000
12
03
1"
#1060000
0"
#1065000
0O
1I
1L
00
1)
11
02
13
1"
#1070000
0"
#1075000
12
03
1"
#1080000
0"
#1085000
10
0)
01
02
13
1"
#1090000
0"
#1095000
12
03
1"
#1100000
0"
#1105000
1(
17
1C
14
1@
1*
05
1=
1-
0A
0+
0>
0.
1G
0P
1J
1,
1K
00
1)
11
02
13
1"
#1110000
0"
#1115000
12
03
1"
#1120000
0"
#1125000
10
0)
01
02
13
1"
#1130000
0"
#1135000
12
03
1"
#1140000
0"
#1145000
0H
0M
1N
00
1)
11
02
13
1"
#1150000
0"
#1155000
12
03
1"
#1160000
0"
#1165000
10
0)
01
02
13
1"
#1170000
0"
#1175000
12
03
1"
#1180000
0"
#1185000
1O
0G
0I
0L
00
1)
11
02
13
1"
#1190000
0"
#1195000
12
03
1"
#1200000
0"
#1205000
10
0)
01
02
13
1"
#1210000
0"
#1215000
12
03
1"
#1220000
0"
#1225000
1P
1H
1M
0,
0K
0N
00
1)
11
02
13
1"
#1230000
0"
#1235000
12
03
1"
#1240000
0"
#1245000
10
0)
01
02
13
1"
#1250000
0"
#1255000
12
03
1"
#1260000
0"
#1265000
0O
1G
1I
1L
00
1)
11
02
13
1"
#1270000
0"
#1275000
12
03
1"
#1280000
0"
#1285000
10
0)
01
02
13
1"
#1290000
0"
#1295000
12
03
1"
#1300000
0"
#1305000
07
1<
09
0;
15
1B
1:
1/
0P
0H
0M
1,
1K
1N
00
1)
11
02
13
1"
#1310000
0"
#1315000
12
03
1"
#1320000
0"
#1325000
10
0)
01
02
13
1"
#1330000
0"
#1335000
12
03
1"
#1340000
0"
#1345000
1O
0G
0I
0L
00
1)
11
02
13
1"
#1350000
0"
#1355000
12
03
1"
#1360000
0"
#1365000
10
0)
01
02
13
1"
#1370000
0"
#1375000
12
03
1"
#1380000
0"
#1385000
1P
1H
1M
0,
0K
0N
00
1)
11
02
13
1"
#1390000
0"
#1395000
12
03
1"
#1400000
0"
#1405000
10
0)
01
02
13
1"
#1410000
0"
#1415000
12
03
1"
#1420000
0"
#1425000
0O
1G
1I
1L
00
1)
11
02
13
1"
#1430000
0"
#1435000
12
03
1"
#1440000
0"
#1445000
10
0)
01
02
13
1"
#1450000
0"
#1455000
12
03
1"
#1460000
0"
#1465000
0(
17
0C
1<
0=
0-
19
1;
05
1>
1.
0B
0:
0/
0P
0H
0M
1,
1K
1N
00
1)
11
02
13
1"
#1470000
0"
#1475000
12
03
1"
#1480000
0"
#1485000
10
0)
01
02
13
1"
#1490000
0"
#1495000
12
03
1"
#1500000
0"
#1505000
1O
0G
0I
0L
00
1)
11
02
13
1"
#1510000
0"
#1515000
12
03
1"
#1520000
0"
#1525000
10
0)
01
02
13
1"
#1530000
0"
#1535000
12
03
1"
#1540000
0"
#1545000
1P
0J
1H
1M
0,
0K
0N
00
1)
11
02
13
1"
#1550000
0"
#1555000
12
03
1"
#1560000
0"
#1565000
10
0)
01
02
13
1"
#1570000
0"
#1575000
12
03
1"
#1580000
0"
#1585000
0O
1I
1L
00
1)
11
02
13
1"
#1590000
0"
#1595000
12
03
1"
#1600000
0"
#1605000
10
0)
01
02
13
1"
#1610000
0"
#1615000
12
03
1"
#1620000
0"
#1625000
0<
07
1?
1(
09
0;
16
15
1B
1:
1/
1G
0P
1J
1,
1K
00
1)
11
02
13
1"
#1630000
0"
#1635000
12
03
1"
#1640000
0"
#1645000
10
0)
01
02
13
1"
#1650000
0"
#1655000
12
03
1"
#1660000
0"
#1665000
0H
0M
1N
00
1)
11
02
13
1"
#1670000
0"
#1675000
12
03
1"
#1680000
0"
#1685000
10
0)
01
02
13
1"
#1690000
0"
#1695000
12
03
1"
#1700000
0"
#1705000
1O
0G
0I
0L
00
1)
11
02
13
1"
#1710000
0"
#1715000
12
03
1"
#1720000
0"
#1725000
10
0)
01
02
13
1"
#1730000
0"
#1735000
12
03
1"
#1740000
0"
#1745000
1H
1M
1P
0N
0,
0K
00
1)
11
02
13
1"
#1750000
0"
#1755000
12
03
1"
#1760000
0"
#1765000
10
0)
01
02
13
1"
#1770000
0"
#1775000
12
03
1"
#1780000
0"
#1785000
0O
1G
1I
1L
00
1)
11
02
13
1"
#1790000
0"
#1795000
12
03
1"
#1800000
0"
#1805000
10
0)
01
02
13
1"
#1810000
0"
#1815000
12
03
1"
#1820000
0"
#1825000
1F
0!
0E
17
0(
0@
0*
1=
1-
19
1;
06
1A
1+
0>
0.
0B
0:
0/
0H
0M
0P
1N
1,
1K
00
1)
11
02
13
1"
#1830000
0"
#1835000
12
03
1"
#1840000
0"
#1845000
10
0)
01
02
13
1"
#1850000
0"
#1855000
12
03
1"
#1860000
0"
#1865000
1O
0G
0I
0L
00
1)
11
02
13
1"
#1870000
0"
#1875000
12
03
1"
#1880000
0"
#1885000
10
0)
01
02
13
1"
#1890000
0"
#1895000
12
03
1"
#1900000
0"
#1905000
1H
1M
1P
0J
0N
0,
0K
00
1)
11
02
13
1"
#1910000
0"
#1915000
12
03
1"
#1920000
0"
#1925000
10
0)
01
02
13
1"
#1930000
0"
#1935000
12
03
1"
#1940000
0"
#1945000
0O
1I
1L
00
1)
11
02
13
1"
#1950000
0"
#1955000
12
03
1"
#1960000
0"
#1965000
10
0)
01
02
13
1"
#1970000
0"
#1975000
12
03
1"
#1980000
0"
#1985000
07
1<
1(
09
0;
1B
1:
1/
1G
0P
1J
1,
1K
00
1)
11
02
13
1"
#1990000
0"
#1995000
12
03
1"
#2000000
0"
#2005000
10
0)
01
02
13
1"
#2010000
0"
#2015000
12
03
1"
#2020000
0"
#2025000
0H
0M
1N
00
1)
11
02
13
1"
#2030000
0"
#2035000
12
03
1"
#2040000
0"
#2045000
10
0)
01
02
13
1"
#2050000
0"
#2055000
12
03
1"
#2060000
0"
#2065000
1O
0G
0I
0L
00
1)
11
02
13
1"
#2070000
0"
#2075000
12
03
1"
#2080000
0"
#2085000
10
0)
01
02
13
1"
#2090000
0"
#2095000
12
03
1"
#2100000
0"
#2105000
1P
1H
1M
0,
0K
0N
00
1)
11
02
13
1"
#2110000
0"
#2115000
12
03
1"
#2120000
0"
#2125000
10
0)
01
02
13
1"
#2130000
0"
#2135000
12
03
1"
#2140000
0"
#2145000
0O
1G
1I
1L
00
1)
11
02
13
1"
#2150000
0"
#2155000
12
03
1"
#2160000
0"
#2165000
10
0)
01
02
13
1"
#2170000
0"
#2175000
12
03
1"
#2180000
0"
#2185000
0?
07
04
0<
0(
0=
0-
19
1;
1>
1.
0B
0:
0/
0P
0H
0M
1,
1K
1N
00
1)
11
02
13
1"
#2190000
0"
#2195000
12
03
1"
#2200000
0"
#2205000
10
0)
01
02
13
1"
#2210000
0"
#2215000
12
03
1"
#2220000
0"
#2225000
1O
0G
0I
0L
00
1)
11
02
13
1"
#2230000
0"
#2235000
12
03
1"
#2240000
0"
#2245000
10
0)
01
02
13
1"
#2250000
0"
#2255000
12
03
1"
#2260000
0"
#2265000
1P
0J
1H
1M
0,
0K
0N
00
1)
11
02
13
1"
#2270000
0"
#2275000
12
03
1"
#2280000
0"
#2285000
10
0)
01
02
13
1"
#2290000
0"
#2295000
12
03
1"
#2300000
0"
#2305000
0O
1I
1L
00
1)
11
02
13
1"
#2310000
0"
#2315000
12
03
1"
#2320000
0"
#2325000
10
0)
01
02
13
1"
#2330000
0"
#2335000
12
03
1"
#2340000
0"
#2345000
1(
17
1C
14
1=
1-
1@
1*
05
0>
0.
0A
0+
1G
0P
1J
1,
1K
00
1)
11
02
13
1"
#2350000
0"
#2355000
12
03
1"
#2360000
0"
#2365000
10
0)
01
02
13
1"
#2370000
0"
#2375000
12
03
1"
#2380000
0"
#2385000
0H
0M
1N
00
1)
11
02
13
1"
#2390000
0"
#2395000
12
03
1"
#2400000
0"
#2405000
10
0)
01
02
13
1"
#2410000
0"
#2415000
12
03
1"
#2420000
0"
#2425000
1O
0G
0I
0L
00
1)
11
02
13
1"
#2430000
0"
#2435000
12
03
1"
#2440000
0"
#2445000
10
0)
01
02
13
1"
#2450000
0"
#2455000
12
03
1"
#2460000
0"
#2465000
1H
1M
1P
0N
0,
0K
00
1)
11
02
13
1"
#2470000
0"
#2475000
12
03
1"
#2480000
0"
#2485000
10
0)
01
02
13
1"
#2490000
0"
#2495000
12
03
1"
#2500000
0"
#2505000
0O
1G
1I
1L
00
1)
11
02
13
1"
#2510000
0"
#2515000
12
03
1"
#2520000
0"
#2525000
10
0)
01
02
13
1"
#2530000
0"
#2535000
12
03
1"
#2540000
0"
#2545000
07
1<
09
0;
15
1B
1:
1/
0H
0M
0P
1N
1,
1K
00
1)
11
02
13
1"
#2550000
0"
#2555000
12
03
1"
#2560000
0"
#2565000
10
0)
01
02
13
1"
#2570000
0"
#2575000
12
03
1"
#2580000
0"
#2585000
1O
0G
0I
0L
00
1)
11
02
13
1"
#2590000
0"
#2595000
12
03
1"
#2600000
0"
#2605000
10
0)
01
02
13
1"
#2610000
0"
#2615000
12
03
1"
#2620000
0"
#2625000
1H
1M
1P
0N
0,
0K
00
1)
11
02
13
1"
#2630000
0"
#2635000
12
03
1"
#2640000
0"
#2645000
10
0)
01
02
13
1"
#2650000
0"
#2655000
12
03
1"
#2660000
0"
#2665000
0O
1G
1I
1L
00
1)
11
02
13
1"
#2670000
0"
#2675000
12
03
1"
#2680000
0"
#2685000
10
0)
01
02
13
1"
#2690000
0"
#2695000
12
03
1"
#2700000
0"
#2705000
0(
17
1<
0C
19
1;
05
0=
0-
0B
0:
0/
1>
1.
0H
0M
0P
1N
1,
1K
00
1)
11
02
13
1"
#2710000
0"
#2715000
12
03
1"
#2720000
0"
#2725000
10
0)
01
02
13
1"
#2730000
0"
#2735000
12
03
1"
#2740000
0"
#2745000
1O
0G
0I
0L
00
1)
11
02
13
1"
#2750000
0"
#2755000
12
03
1"
#2760000
0"
#2765000
10
0)
01
02
13
1"
#2770000
0"
#2775000
12
03
1"
#2780000
0"
#2785000
1H
1M
1P
0J
0N
0,
0K
00
1)
11
02
13
1"
#2790000
0"
#2795000
12
03
1"
#2800000
0"
#2805000
10
0)
01
02
13
1"
#2810000
0"
#2815000
12
03
1"
#2820000
0"
#2825000
0O
1I
1L
00
1)
11
02
13
1"
#2830000
0"
#2835000
12
03
1"
#2840000
0"
#2845000
10
0)
01
02
13
1"
#2850000
0"
#2855000
12
03
1"
#2860000
0"
#2865000
0<
07
1?
1(
09
0;
16
15
1B
1:
1/
1G
0P
1J
1,
1K
00
1)
11
02
13
1"
#2870000
0"
#2875000
12
03
1"
#2880000
0"
#2885000
10
0)
01
02
13
1"
#2890000
0"
#2895000
12
03
1"
#2900000
0"
#2905000
0H
0M
1N
00
1)
11
02
13
1"
#2910000
0"
#2915000
12
03
1"
#2920000
0"
#2925000
10
0)
01
02
13
1"
#2930000
0"
#2935000
12
03
1"
#2940000
0"
#2945000
1O
0G
0I
0L
00
1)
11
02
13
1"
#2950000
0"
#2955000
12
03
1"
#2960000
0"
#2965000
10
0)
01
02
13
1"
#2970000
0"
#2975000
12
03
1"
#2980000
0"
