schematic/dsm/src/Modulus_Controller.v
// ===============================================
// Module 4: Modulus Controller
// Decodes counter state to control Prescaler (MC)
// ===============================================

module Modulus_Controller (
    input wire b, // LSB
    input wire c,
    input wire d, // MSB
    input wire c_bar,
    input wire d_bar,
    input wire select_in,  // 1->240, 0->248
    output wire mc
);
    wire logic_0, logic_1, logic_2;

    assign logic_0 = b;
    assign logic_1 = c_bar & d_bar;
    assign logic_2 = c & d & select_in;
    
    assign mc = logic_0 | logic_1 | logic_2;
endmodule

schematic/freq_divider/testbenches/tb_Modulus_Controller.v
`timescale 1ns/1ps
`include "../../Modulus_Controller.v"

module tb_Modulus_Controller;
    // Inputs
    reg b, c, d;
    reg c_bar, d_bar;
    reg select_in;
    // Outputs
    wire mc;

    // Instantiate the Unit Under Test (UUT)
    Modulus_Controller uut (
        .b(b), 
        .c(c), 
        .d(d),
        .c_bar(c_bar),
        .d_bar(d_bar), 
        .select_in(select_in), 
        .mc(mc)
    );

    initial begin
        $dumpfile("tb_Modulus_Controller.vcd");
        $dumpvars;

        // Initialize Inputs
        {b, c, d, c_bar, d_bar} = 5'b00000; #10;

        select_in = 1; #10; // Divide by 240 mode
        // Test Case 1.1
        b = 1'b1; #10; // Expect MC=1
        // Test Case 1.2
        {b, c_bar, d_bar} = 3'b011; #10; // Expect MC=1
        // Test Case 1.3
        {c, d, c_bar, d_bar} = 4'b1100; #10; // Expect MC=1

        select_in = 0; // Divide by 248 mode
        // Test Case 1.1
        b = 1'b1; #10; // Expect MC=1
        // Test Case 1.2
        {b, c_bar, d_bar} = 3'b011; #10; // Expect MC=1
        // Test Case 1.3
        {c, d, c_bar, d_bar} = 4'b1100; #10; // Expect MC=0

        $finish;
    end
endmodule

xschem/freq_divider/testbenches/vcd/tb_Modulus_Controller.vcd
$date
	Sat Feb  7 12:15:58 2026
$end
$version
	Icarus Verilog
$end
$timescale
	1ps
$end
$scope module tb_Modulus_Controller $end
$var wire 1 ! mc $end
$var reg 1 " b $end
$var reg 1 # c $end
$var reg 1 $ c_bar $end
$var reg 1 % d $end
$var reg 1 & d_bar $end
$var reg 1 ' select_in $end
$scope module uut $end
$var wire 1 " b $end
$var wire 1 # c $end
$var wire 1 $ c_bar $end
$var wire 1 % d $end
$var wire 1 & d_bar $end
$var wire 1 ( logic_0 $end
$var wire 1 ) logic_1 $end
$var wire 1 * logic_2 $end
$var wire 1 ! mc $end
$var wire 1 ' select_in $end
$upscope $end
$upscope $end
$enddefinitions $end
$comment Show the parameter values. $end
$dumpall
$end
#0
$dumpvars
0*
0)
0(
x'
0&
0%
0$
0#
0"
0!
$end
#10000
1'
#20000
1!
1(
1"
#30000
1)
0(
0"
1$
1&
#40000
1*
0)
1#
1%
0$
0&
#50000
0*
1(
1"
0'
#60000
1)
0(
0"
1$
1&
#70000
0!
0)
0$
0&
