xschem/dsm/src/DFF.v
// ========================================================
// Basic Building Block: D Flip-Flop with Active High Reset
// ========================================================

module DFF (
    input wire clk,
    input wire rst,
    input wire d,
    output reg q,
    output wire q_bar
);
    assign q_bar = ~q;

    always @(posedge clk or posedge rst) begin
        if (rst)
            q <= 1'b0;
        else
            q <= d;
    end
endmodule

xschem/freq_divider/testbenches/tb_DFF.v
`timescale 1ns/1ps
`include "../../DFF.v"

module tb_DFF;

    // Inputs
    reg clk;
    reg rst;
    reg d;
    // Outputs
    wire q;
    wire q_bar;

    // Instantiate the Unit Under Test (UUT)
    DFF uut (
        .clk(clk), 
        .rst(rst), 
        .d(d), 
        .q(q), 
        .q_bar(q_bar)
    );

    // Clock generation
    always #5 clk = ~clk;

    initial begin
        $dumpfile("tb_DFF.vcd");
        $dumpvars;

        // Initialize Inputs
        clk = 0;
        rst = 1;
        d = 0;

        // Wait 20ns for global reset to finish
        #20;
        rst = 0;

        // Test 1: Set D=1
        #10 d = 1;
        
        // Test 2: Set D=0
        #8 d = 0;
        
        // Test 3: Set D=1 again
        #10 d = 1;
        
        // Test 4: Assert Reset while D is high (Asynchronous check)
        #10 rst = 1;
        #10 rst = 0;

        #7;
        $finish;
    end
endmodule

schematic/freq_divider/testbenches/vcd/tb_DFF.vcd
$date
	Sat Feb  7 08:31:49 2026
$end
$version
	Icarus Verilog
$end
$timescale
	1ps
$end
$scope module tb_DFF $end
$var wire 1 ! q_bar $end
$var wire 1 " q $end
$var reg 1 # clk $end
$var reg 1 $ d $end
$var reg 1 % rst $end
$scope module uut $end
$var wire 1 # clk $end
$var wire 1 $ d $end
$var wire 1 ! q_bar $end
$var wire 1 % rst $end
$var reg 1 " q $end
$upscope $end
$upscope $end
$enddefinitions $end
$comment Show the parameter values. $end
$dumpall
$end
#0
$dumpvars
1%
0$
0#
0"
1!
$end
#5000
1#
#10000
0#
#15000
1#
#20000
0#
0%
#25000
1#
#30000
0#
1$
#35000
0!
1"
1#
#38000
0$
#40000
0#
#45000
1!
0"
1#
#48000
1$
#50000
0#
#55000
0!
1"
1#
#58000
1!
0"
1%
#60000
0#
#65000
1#
#68000
0%
#70000
0#
#75000
0!
1"
1#
