xschem/dsm/src/DFF.v
// ========================================================
// Basic Building Block: D Flip-Flop with Active High Reset
// ========================================================

module DFF (
    input wire clk,
    input wire rst,
    input wire d,
    output reg q,
    output wire q_bar
);
    assign q_bar = ~q;

    always @(posedge clk or posedge rst) begin
        if (rst)
            q <= 1'b0;
        else
            q <= d;
    end
endmodule

xschem/dsm/src/JK_FF.v
// =========================================================
// Basic Building Block: JK Flip-Flop (Constructed from DFF)
// =========================================================
//`include "DFF.v"

module JK_FF (
    input wire clk,
    input wire rst,
    input wire j,
    input wire k,
    output wire q,
    output wire q_bar
);
    wire d_in;
    wire q_curr, q_bar_curr;
    
    // Logic: D = J & ~Q | ~K & Q
    assign d_in = (j & q_bar_curr) | (~k & q_curr);
    
    DFF dff_inst (
        .clk(clk),
        .rst(rst),
        .d(d_in),
        .q(q),
        .q_bar(q_bar)
    );
    
    // Internal wiring to allow feedback
    assign q_curr = q;
    assign q_bar_curr = q_bar;
endmodule

schematic/freq_divider/testbenches/tb_JK_FF.v
`timescale 1ns/1ps
`include "../../JK_FF.v"

module tb_JK_FF;
    // Inputs
    reg clk;
    reg rst;
    reg j;
    reg k;
    // Outputs
    wire q;
    wire q_bar;

    // Instantiate the Unit Under Test (UUT)
    JK_FF uut (
        .clk(clk), 
        .rst(rst), 
        .j(j), 
        .k(k), 
        .q(q), 
        .q_bar(q_bar)
    );

    // Clock generation
    always #5 clk = ~clk;

    initial begin
        $dumpfile("tb_JK_FF.vcd");
        $dumpvars;

        // Initialize Inputs
        clk = 0;
        rst = 1;
        j = 0; k = 0;

        // Wait 20ns for global reset to finish
        #20;
        rst = 0;

        // Case 1: Set (J=1, K=0) -> Q should become 1
        #10 j = 1; k = 0;
        
        // Case 2: Toggle (J=1, K=1) -> Q should invert
        #10 j = 1; k = 1;
        #10; // Wait one clock
        #10; // Wait another clock to see toggling
        #10; // Now Q should be back to 1

        // Case 3: Reset (J=0, K=1) -> Q should become 0
        #10 j = 0; k = 1;

        // Case 4: Hold (J=0, K=0) -> Q should stay 0
        #10 j = 0; k = 0;
        
        // Set to 1 then Hold
        #10 j = 1; k = 0; // Set
        #10 j = 0; k = 0; // Hold (should stay 1)

        #20;
        $finish;
    end
endmodule

schematic/freq_divider/testbenches/vcd/tb_JK_FF.vcd
$date
	Sat Feb  7 08:42:10 2026
$end
$version
	Icarus Verilog
$end
$timescale
	1ps
$end
$scope module tb_JK_FF $end
$var wire 1 ! q_bar $end
$var wire 1 " q $end
$var reg 1 # clk $end
$var reg 1 $ j $end
$var reg 1 % k $end
$var reg 1 & rst $end
$scope module uut $end
$var wire 1 # clk $end
$var wire 1 ' d_in $end
$var wire 1 $ j $end
$var wire 1 % k $end
$var wire 1 ( q_bar_curr $end
$var wire 1 ) q_curr $end
$var wire 1 & rst $end
$var wire 1 ! q_bar $end
$var wire 1 " q $end
$scope module dff_inst $end
$var wire 1 # clk $end
$var wire 1 ' d $end
$var wire 1 ! q_bar $end
$var wire 1 & rst $end
$var reg 1 " q $end
$upscope $end
$upscope $end
$upscope $end
$enddefinitions $end
$comment Show the parameter values. $end
$dumpall
$end
#0
$dumpvars
0)
1(
0'
1&
0%
0$
0#
0"
1!
$end
#5000
1#
#10000
0#
#15000
1#
#20000
0#
0&
#25000
1#
#30000
1'
0#
1$
#35000
0(
0!
1)
1"
1#
#40000
0'
0#
1%
#45000
1'
1(
1!
0)
0"
1#
#50000
0#
#55000
0'
0(
0!
1)
1"
1#
#60000
0#
#65000
1'
1(
1!
0)
0"
1#
#70000
0#
#75000
0'
0(
0!
1)
1"
1#
#80000
0#
0$
#85000
1(
1!
0)
0"
1#
#90000
0#
0%
#95000
1#
#100000
1'
0#
1$
#105000
0(
0!
1)
1"
1#
#110000
0#
0$
